dakora/__init__.py
dakora/cli.py
dakora/exceptions.py
dakora/logging.py
dakora/model.py
dakora/playground.py
dakora/renderer.py
dakora/types.py
dakora/vault.py
dakora/watcher.py
dakora/llm/__init__.py
dakora/llm/client.py
dakora/llm/models.py
dakora/registry/__init__.py
dakora/registry/base.py
dakora/registry/core.py
dakora/registry/serialization.py
dakora/registry/backends/__init__.py
dakora/registry/backends/azure.py
dakora/registry/backends/base.py
dakora/registry/backends/local.py
dakora/registry/implementations/__init__.py
dakora/registry/implementations/azure.py
dakora/registry/implementations/local.py
dakora-1.0.3.dist-info/METADATA
dakora-1.0.3.dist-info/WHEEL
dakora-1.0.3.dist-info/entry_points.txt
dakora-1.0.3.dist-info/licenses/LICENSE
dakora-1.0.3.dist-info/RECORD
