Metadata-Version: 2.4
Name: dakora
Version: 1.0.3
Summary: A Python library for managing and rendering prompt templates with type-safe inputs, versioning, and optional logging
Project-URL: Homepage, https://github.com/bogdan-pistol/dakora
Project-URL: Repository, https://github.com/bogdan-pistol/dakora.git
Project-URL: Issues, https://github.com/bogdan-pistol/dakora/issues
Author-email: bogdanpi <bogdan@iduntechnologies.com>
License-File: LICENSE
Classifier: Development Status :: 4 - Beta
Classifier: Intended Audience :: Developers
Classifier: License :: OSI Approved :: Apache Software License
Classifier: Programming Language :: Python :: 3
Classifier: Programming Language :: Python :: 3.11
Classifier: Programming Language :: Python :: 3.12
Requires-Python: >=3.11
Requires-Dist: fastapi>=0.104.0
Requires-Dist: jinja2>=3.1.6
Requires-Dist: litellm>=1.0.0
Requires-Dist: pydantic>=2.11.9
Requires-Dist: python-dotenv>=1.0.0
Requires-Dist: pyyaml>=6.0.2
Requires-Dist: typer>=0.19.2
Requires-Dist: uvicorn>=0.24.0
Requires-Dist: watchdog>=6.0.0
Provides-Extra: azure
Requires-Dist: azure-identity>=1.15.0; extra == 'azure'
Requires-Dist: azure-storage-blob>=12.19.0; extra == 'azure'
